setup.py
cql_shifter.egg-info/PKG-INFO
cql_shifter.egg-info/SOURCES.txt
cql_shifter.egg-info/dependency_links.txt
cql_shifter.egg-info/entry_points.txt
cql_shifter.egg-info/requires.txt
cql_shifter.egg-info/top_level.txt
shifter/__init__.py
shifter/__main__.py
shifter/cli.py
shifter/config.py
shifter/db.py
shifter/map.py
shifter/migrate.py