Metadata-Version: 1.1
Name: cql-shifter
Version: 0.2
Summary: A tool for migration management with Cassandra
Home-page: http://github.com/rgamba/shift/
Author: Ricardo Gamba
Author-email: rgamba@gmail.com
License: MIT
Keywords: development database migration cassandra
Platform: UNKNOWN
Classifier: Development Status :: 3 - Alpha
Classifier: Intended Audience :: Developers
Classifier: License :: OSI Approved :: BSD License
Classifier: Programming Language :: Python
Classifier: Programming Language :: Python :: 2
Classifier: Programming Language :: Python :: 2.6
Classifier: Programming Language :: Python :: 2.7
